dirichletprocess-0.2.0.dist-info/DESCRIPTION.rst
dirichletprocess-0.2.0.dist-info/METADATA
dirichletprocess-0.2.0.dist-info/metadata.json
dirichletprocess-0.2.0.dist-info/RECORD
dirichletprocess-0.2.0.dist-info/top_level.txt
dirichletprocess-0.2.0.dist-info/WHEEL
dp/__init__.py
dp/dirichlet.py
