Metadata-Version: 2.0
Name: dirichletprocess
Version: 0.2.0
Summary: Tools for Dirichlet Processes
Home-page: https://github.com/tdhopper/dirichlet
Author: Tim Hopper
Author-email: tdhopper@gmail.com
License: MIT
Keywords: dirichlet process
Platform: UNKNOWN
Classifier: Development Status :: 2 - Pre-Alpha
Classifier: Intended Audience :: Developers
Classifier: License :: OSI Approved :: MIT License
Classifier: Natural Language :: English
Classifier: Programming Language :: Python :: 2
Classifier: Programming Language :: Python :: 2.7
Classifier: Programming Language :: Python :: 3
Classifier: Programming Language :: Python :: 3.3
Classifier: Programming Language :: Python :: 3.4
